LICENSE
MANIFEST.in
README.md
pyproject.toml
setup.cfg
mistapi/__init__.py
mistapi/api_helper.py
mistapi/configuration.py
mistapi/mistapi_client.py
mistapi/controllers/__init__.py
mistapi/controllers/admin_controller.py
mistapi/controllers/api_token_controller.py
mistapi/controllers/base_controller.py
mistapi/controllers/constants_controller.py
mistapi/controllers/installer_controller.py
mistapi/controllers/login_controller.py
mistapi/controllers/login_with_o_auth_2_controller.py
mistapi/controllers/mobile_controller.py
mistapi/controllers/msps_admins_controller.py
mistapi/controllers/msps_controller.py
mistapi/controllers/msps_inventory_controller.py
mistapi/controllers/msps_invites_controller.py
mistapi/controllers/msps_licenses_controller.py
mistapi/controllers/msps_logo_controller.py
mistapi/controllers/msps_logs_controller.py
mistapi/controllers/msps_marvis_controller.py
mistapi/controllers/msps_org_groups_controller.py
mistapi/controllers/msps_orgs_controller.py
mistapi/controllers/msps_sl_es_controller.py
mistapi/controllers/msps_sso_controller.py
mistapi/controllers/msps_sso_roles_controller.py
mistapi/controllers/msps_stats_controller.py
mistapi/controllers/msps_tickets_controller.py
mistapi/controllers/orgs_admin_controller.py
mistapi/controllers/orgs_admins_controller.py
mistapi/controllers/self_controller.py
mistapi/controllers/sites_alarms_controller.py
mistapi/controllers/sites_anomaly_controller.py
mistapi/controllers/sites_applications_controller.py
mistapi/controllers/sites_asset_filters_controller.py
mistapi/controllers/sites_assets_controller.py
mistapi/controllers/sites_beacons_controller.py
mistapi/controllers/sites_calls_controller.py
mistapi/controllers/sites_clients_wan_controller.py
mistapi/controllers/sites_clients_wired_controller.py
mistapi/controllers/sites_clients_wireless_controller.py
mistapi/controllers/sites_controller.py
mistapi/controllers/sites_devices_controller.py
mistapi/controllers/sites_devices_others_controller.py
sdksio_juniper_mist_sdk.egg-info/PKG-INFO
sdksio_juniper_mist_sdk.egg-info/SOURCES.txt
sdksio_juniper_mist_sdk.egg-info/dependency_links.txt
sdksio_juniper_mist_sdk.egg-info/requires.txt
sdksio_juniper_mist_sdk.egg-info/top_level.txt