Metadata-Version: 2.1
Name: sdksio-juniper-mist-sdk
Version: 1.0.0
Summary: Use the Juniper Mist SDK to automate many Mist processes by using the RESTful API, webhooks, and the WebSocket API.
Author-email: developer-sdksio <developer+sdksio@apimatic.io>
Project-URL: Documentation, https://www.apimatic.io/api-docs/juniper-mist
Keywords: juniper networks,mist api,sdksio
Requires-Python: >=3.7
Provides-Extra: testutils
License-File: LICENSE
